LICENSE.txt
MANIFEST.in
README.md
setup.py
django_registration_names.egg-info/PKG-INFO
django_registration_names.egg-info/SOURCES.txt
django_registration_names.egg-info/dependency_links.txt
django_registration_names.egg-info/not-zip-safe
django_registration_names.egg-info/requires.txt
django_registration_names.egg-info/top_level.txt
registration_names/__init__.py
registration_names/checkers.py
registration_names/forms.py
registration_names/tests.py
registration_names/backends/__init__.py
registration_names/backends/utils.py
registration_names/backends/default/__init__.py
registration_names/backends/default/urls.py
registration_names/backends/simple/__init__.py
registration_names/backends/simple/urls.py