Metadata-Version: 1.1
Name: django-registration-names
Version: 0.1b
Summary: A way to control allowed and prohibited user names for registration with django-registration.
Home-page: https://github.com/ivanyu/django-registration-names
Author: Ivan Yurchenko <ivan0yurchenko@gmail.com>
Author-email: ivan0yurchenko@gmail.com
License: MIT License
Keywords: django,django-registration
Platform: UNKNOWN
Classifier: Framework :: Django
Classifier: Programming Language :: Python
Classifier: Environment :: Web Environment
Classifier: Intended Audience :: Developers
Classifier: Development Status :: 4 - Beta
Classifier: License :: OSI Approved :: MIT License
Classifier: Operating System :: OS Independent
Classifier: Topic :: Software Development :: Libraries :: Python Modules
